loggy/__init__.py
loggy/exceptions.py
loggy/loggy.py
get_loggy-0.0.5.dist-info/LICENSE
get_loggy-0.0.5.dist-info/METADATA
get_loggy-0.0.5.dist-info/WHEEL
get_loggy-0.0.5.dist-info/top_level.txt
get_loggy-0.0.5.dist-info/RECORD
