Metadata-Version: 2.1
Name: get-loggy
Version: 0.0.5
Summary: A simple logging utility.
Home-page: https://github.com/mattdood/loggy
Author: Matthew Wimberly
Author-email: matthew.wimb@gmail.com
Project-URL: Bug Tracker, https://github.com/mattdood/loggy/issues
Classifier: Programming Language :: Python :: 3
Classifier: License :: OSI Approved :: MIT License
Classifier: Operating System :: OS Independent
Requires-Python: >=3.6
License-File: LICENSE
